ha.v
module ha(a,b,sum,carry);

input a,b;
output sum,carry;

assign sum=a^b;
assign carry=a&b;

endmodule

fa_using_ha.v
module fa_using_ha;

reg a,b,cin;
wire s,c;

wire s1,c1,c2;

ha iha1(a,b,s1,c1);
ha iha2(s1,cin,s,c2);

assign c=c1|c2;

initial begin
    a=0;b=0;cin=0; #10
    a=1; #10
    a=0;b=1; #10
    a=1; #10
    a=0;b=0;cin=1; #10
    a=1; #10
    a=0;b=1; #10
    a=1; #10
    $finish;
    $dumpflush;
end
initial begin
    $monitor($time,"a=%b b=%b cin=%b sum=%b carry=%b",a,b,cin,s,c);
    $dumpfile("decoder.vcd");
    $dumpvars(0,fa_using_ha);
end
endmodule

decoder.vcd
$date
	Thu Feb 17 22:25:44 2022
$end
$version
	Icarus Verilog
$end
$timescale
	1s
$end
$scope module fa_using_ha $end
$var wire 1 ! c $end
$var wire 1 " s1 $end
$var wire 1 # s $end
$var wire 1 $ c2 $end
$var wire 1 % c1 $end
$var reg 1 & a $end
$var reg 1 ' b $end
$var reg 1 ( cin $end
$scope module iha1 $end
$var wire 1 & a $end
$var wire 1 ' b $end
$var wire 1 % carry $end
$var wire 1 " sum $end
$upscope $end
$scope module iha2 $end
$var wire 1 " a $end
$var wire 1 ( b $end
$var wire 1 $ carry $end
$var wire 1 # sum $end
$upscope $end
$upscope $end
$enddefinitions $end
#0
$dumpvars
0(
0'
0&
0%
0$
0#
0"
0!
$end
#10
1#
1"
1&
#20
1'
0&
#30
0#
1!
0"
1%
1&
#40
0!
1#
0%
1(
0'
0&
#50
1!
0#
1$
1"
1&
#60
1'
0&
#70
1#
0$
0"
1%
1&
