decoder_3to8.v
module decoder_3to8(sel,out);

input [2:0]sel;
reg [7:0]y;
output [7:0]out;

always@(sel) begin
    if(sel==3'b000) y<=8'b00000001;
    else if(sel==3'b001) y<=8'b00000010;
    else if(sel==3'b010) y<=8'b00000100;
    else if(sel==3'b011) y<=8'b00001000;
    else if(sel==3'b100) y<=8'b00010000;
    else if(sel==3'b101) y<=8'b00100000;
    else if(sel==3'b110) y<=8'b01000000;
    else if(sel==3'b111) y<=8'b10000000;
end

assign out=y;
endmodule

test_decoder_3to8.v
module test_decoder_3to8;

reg [2:0]sel;
wire [7:0]y;

decoder_3to8 idecoder_3to8(sel,y);

initial begin
    sel=3'b000;
    #10 sel=3'b001;
    #10 sel=3'b010;
    #10 sel=3'b011;
    #10 sel=3'b100;
    #10 sel=3'b101;
    #10 sel=3'b110;
    #10 sel=3'b111;
    #10
    $finish;
    $dumpflush;
end
initial begin
    $monitor($time,"sel=%b y=%b",sel,y);
    $dumpfile("test_decoder.vcd");
    $dumpvars(0,test_decoder_3to8);
end
endmodule

test_decoder.vcd
$date
	Thu Feb 17 22:09:14 2022
$end
$version
	Icarus Verilog
$end
$timescale
	1s
$end
$scope module test_decoder_3to8 $end
$var wire 8 ! y [7:0] $end
$var reg 3 " sel [2:0] $end
$scope module idecoder_3to8 $end
$var wire 8 # out [7:0] $end
$var wire 3 $ sel [2:0] $end
$var reg 8 % y [7:0] $end
$upscope $end
$upscope $end
$enddefinitions $end
#0
$dumpvars
b1 %
b0 $
b1 #
b0 "
b1 !
$end
#10
b10 !
b10 #
b10 %
b1 "
b1 $
#20
b100 !
b100 #
b100 %
b10 "
b10 $
#30
b1000 !
b1000 #
b1000 %
b11 "
b11 $
#40
b10000 !
b10000 #
b10000 %
b100 "
b100 $
#50
b100000 !
b100000 #
b100000 %
b101 "
b101 $
#60
b1000000 !
b1000000 #
b1000000 %
b110 "
b110 $
#70
b10000000 !
b10000000 #
b10000000 %
b111 "
b111 $
