mux8to1.v
module mux8to1(a,sel,y);

input [7:0]a;
input [2:0]sel;
output y;
reg out;

always@(sel[0] or sel[1] or sel[2])
    if(sel==3'b000) out<=a[0];
    else if(sel==3'b001) out<=a[1];
    else if(sel==3'b010) out<=a[2];
    else if(sel==3'b011) out<=a[3];
    else if(sel==3'b100) out<=a[4];
    else if(sel==3'b101) out<=a[5];
    else if(sel==3'b110) out<=a[6];
    else if(sel==3'b111) out<=a[7];

assign y=out;
endmodule

test_mux8to1.v
module test_mux8to1;
reg [7:0]in;
reg [2:0]sel;
wire out;

mux8to1 imux8to1(in,sel,out);

initial begin
    in=8'b10100111;
    sel=3'b000;
    #10 sel=3'b001;
    #10 sel=3'b010;
    #10 sel=3'b011;
    #10 sel=3'b100;
    #10 sel=3'b101;
    #10 sel=3'b110;
    #10 sel=3'b111;
    #10
    $dumpflush;
    $finish;
end
initial begin
    $monitor($time, "in=%b sel=%b out=%b",in,sel,out);
    $dumpfile("test_mux8to1.vcd");
    $dumpvars(0,test_mux8to1);
end
endmodule

test_mux8to1.vcd
$date
	Wed Feb 09 23:03:42 2022
$end
$version
	Icarus Verilog
$end
$timescale
	1s
$end
$scope module test_mux8to1 $end
$var wire 1 ! out $end
$var reg 8 " in [7:0] $end
$var reg 3 # sel [2:0] $end
$scope module imux8to1 $end
$var wire 8 $ a [7:0] $end
$var wire 3 % sel [2:0] $end
$var wire 1 ! y $end
$var reg 1 & out $end
$upscope $end
$upscope $end
$enddefinitions $end
#0
$dumpvars
1&
b0 %
b10100111 $
b0 #
b10100111 "
1!
$end
#10
b1 #
b1 %
#20
b10 #
b10 %
#30
0!
0&
b11 #
b11 %
#40
b100 #
b100 %
#50
1!
1&
b101 #
b101 %
#60
0!
0&
b110 #
b110 %
#70
1!
1&
b111 #
b111 %
