half_adder.v
module half_adder(s,c,a,b);
input a,b;
output s,c;

assign #3 s = a^b;
assign #2 c = a&b;

endmodule

test_half_adder.v
module test_half_adder;

reg a,b;
wire s,c;

half_adder ihalf_adder(s,c,a,b);

initial begin
    a=0;
    b=0;
    #10 b=1;
    #10 a=1;b=0;
    #10 b=1;
    #10
    $dumpflush;
    $finish;
end
initial begin
    $monitor($time, "a=%b b=%b s=%b c=%b",a,b,s,c);
    $dumpfile("test_half_adder.vcd");
    $dumpvars(0,test_half_adder);
end
endmodule

test_half_adder.vcd
$date
	Fri Nov 12 14:58:23 2021
$end
$version
	Icarus Verilog
$end
$timescale
	1s
$end
$scope module test_half_adder $end
$var wire 1 ! s $end
$var wire 1 " c $end
$var reg 1 # a $end
$var reg 1 $ b $end
$scope module ihalf_adder $end
$var wire 1 # a $end
$var wire 1 $ b $end
$var wire 1 " c $end
$var wire 1 ! s $end
$upscope $end
$upscope $end
$enddefinitions $end
#0
$dumpvars
0$
0#
x"
x!
$end
#2
0"
#3
0!
#10
1$
#13
1!
#20
0$
1#
#30
1$
#32
1"
#33
0!
