fa.v
module fa(a,b,cin,s,c);

input a,b,cin;
output s,c;
reg sum,carry;

always@(a or b or cin) begin
    sum<=a^b;
    carry<=a&b;
end
assign s=(sum^cin);
assign c=(carry)|(sum&cin);

endmodule

test_fa.v
module test_fa;

reg a,b,cin;
wire s,c;

fa ifa(a,b,cin,s,c);

initial begin
    a=0;b=0;cin=0;
    #10 a=1;
    #10 a=1; b=1;
    #10 a=0;
    #10 cin=1;b=0;
    #10 a=1;
    #10 a=1; b=1;
    #10 a=0;
    #10
    $finish;
    $dumpflush;
end
initial begin
    $monitor($time, "a=%b b=%b cin=%b sum=%b carry=%b",a,b,cin,s,c);
    $dumpfile("test_fa.vcd");
    $dumpvars(0,test_fa);
end
endmodule

test_fa.vcd
$date
	Thu Feb 17 21:06:06 2022
$end
$version
	Icarus Verilog
$end
$timescale
	1s
$end
$scope module test_fa $end
$var wire 1 ! s $end
$var wire 1 " c $end
$var reg 1 # a $end
$var reg 1 $ b $end
$var reg 1 % cin $end
$scope module ifa $end
$var wire 1 # a $end
$var wire 1 $ b $end
$var wire 1 " c $end
$var wire 1 % cin $end
$var wire 1 ! s $end
$var reg 1 & carry $end
$var reg 1 ' sum $end
$upscope $end
$upscope $end
$enddefinitions $end
#0
$dumpvars
0'
0&
0%
0$
0#
0"
0!
$end
#10
1!
1'
1#
#20
1"
0!
1&
0'
1$
#30
0"
1!
0&
1'
0#
#40
0'
0"
1!
0$
1%
#50
1"
0!
1'
1#
#60
1!
1&
0'
1$
#70
0!
0&
1'
0#
